{
  "nomination": {
    "name": "Сеты",
    "element": [
      {
        "id": "1",
        "name": "Сет токио",
        "about": "Калифорния классическая 1, лосось 1, Филадельфия спешл 1/2, зеленая река 1/2, вот",
        "weight": "636грам",
        "amount": "25",
        "image": "https://xn--80adjkr6adm9b.xn--p1ai/pics/5f6336a1e4b00367245dbcf1?width=300",
        "person": "2",
        "price": "615"
      },
      {
        "id": "2",
        "name": "Сет токио",
        "about": "Калифорния классическая 1, лосось 1, Филадельфия спешл 1/2, зеленая река 1/2, вот",
        "weight": "636грам",
        "amount": "25",
        "image": "https://xn--80adjkr6adm9b.xn--p1ai/pics/5f6336a1e4b00367245dbcf1?width=300",
        "person": "3",
        "price": "615"
      },
      {
        "id": "3",
        "name": "Сет токио",
        "about": "Калифорния классическая 1, лосось 1, Филадельфия спешл 1/2, зеленая река 1/2, вот",
        "weight": "636грам",
        "amount": "25",
        "image": "https://xn--80adjkr6adm9b.xn--p1ai/pics/5f6336a1e4b00367245dbcf1?width=300",
        "person": "4",
        "price": "615"
      },
      {
        "id": "4",
        "name": "Сет токио",
        "about": "Калифорния классическая 1, лосось 1, Филадельфия спешл 1/2, зеленая река 1/2, вот",
        "weight": "636грам",
        "amount": "25",
        "image": "https://xn--80adjkr6adm9b.xn--p1ai/pics/5f6336a1e4b00367245dbcf1?width=300",
        "person": "1",
        "price": "615"
      },
      {
        "id": "5",
        "name": "Сет токио",
        "about": "Калифорния классическая 1, лосось 1, Филадельфия спешл 1/2, зеленая река 1/2, вот",
        "weight": "636грам",
        "amount": "25",
        "image": "https://xn--80adjkr6adm9b.xn--p1ai/pics/5f6336a1e4b00367245dbcf1?width=300",
        "person": "2",
        "price": "2312"
      },
      {
        "id": "6",
        "name": "Сет токио",
        "about": "Калифорния классическая 1, лосось 1, Филадельфия спешл 1/2, зеленая река 1/2, вот",
        "weight": "636грам",
        "amount": "25",
        "image": "https://xn--80adjkr6adm9b.xn--p1ai/pics/5f6336a1e4b00367245dbcf1?width=300",
        "person": "2",
        "price": "615"
      },
      {
        "id": "7",
        "name": "Сет токио",
        "about": "Калифорния классическая 1, лосось 1, Филадельфия спешл 1/2, зеленая река 1/2, вот",
        "weight": "636грам",
        "amount": "25",
        "image": "https://xn--80adjkr6adm9b.xn--p1ai/pics/5f6336a1e4b00367245dbcf1?width=300",
        "person": "2",
        "price": "615"
      },
      {
        "id": "8",
        "name": "Сет токио",
        "about": "Калифорния классическая 1, лосось 1, Филадельфия спешл 1/2, зеленая река 1/2, вот",
        "weight": "636грам",
        "amount": "25",
        "image": "https://xn--80adjkr6adm9b.xn--p1ai/pics/5f6336a1e4b00367245dbcf1?width=300",
        "person": "2",
        "price": "615"
      },
      {
        "id": "9",
        "name": "Сет токио",
        "about": "Калифорния классическая 1, лосось 1, Филадельфия спешл 1/2, зеленая река 1/2, вот",
        "weight": "636грам",
        "amount": "25",
        "image": "https://xn--80adjkr6adm9b.xn--p1ai/pics/5f6336a1e4b00367245dbcf1?width=300",
        "person": "2",
        "price": "615"
      }
    ]
  }

}
